crazytext/__init__.py
crazytext/utils.py
crazytext/data/abbreviations_wordlist.json
crazytext-1.0.4.dist-info/LICENSE
crazytext-1.0.4.dist-info/METADATA
crazytext-1.0.4.dist-info/WHEEL
crazytext-1.0.4.dist-info/top_level.txt
crazytext-1.0.4.dist-info/RECORD
