Metadata-Version: 2.1
Name: crazytext
Version: 1.0.4
Summary: An Easy To Use Text Cleaning Package For NLP
Home-page: https://github.com/Abhayparashar31
Author: Abhay Parashar
Author-email: parasharabhay13@gmail.com
License: UNKNOWN
Platform: UNKNOWN
Classifier: Programming Language :: Python :: 3
Classifier: License :: OSI Approved :: MIT License
Classifier: Operating System :: OS Independent
Requires-Python: >=3.7
License-File: LICENSE
